splitpo/__init__.py
splitpo/common.py
splitpo/join.py
splitpo/split.py
splitpo-0.1.0.dist-info/METADATA
splitpo-0.1.0.dist-info/WHEEL
splitpo-0.1.0.dist-info/entry_points.txt
splitpo-0.1.0.dist-info/licenses/LICENSE
splitpo-0.1.0.dist-info/RECORD
