Metadata-Version: 2.4
Name: splitpo
Version: 0.1.0
Summary: Splitting gettext .po files into smaller 
Project-URL: Homepage, https://github.com/atsuoishimoto/pyprod
License-File: LICENSE
Requires-Python: >=3.10
